airflow/providers/mysql/__init__.py
airflow/providers/mysql/get_provider_info.py
airflow/providers/mysql/version_compat.py
airflow/providers/mysql/assets/__init__.py
airflow/providers/mysql/assets/mysql.py
airflow/providers/mysql/hooks/__init__.py
airflow/providers/mysql/hooks/mysql.py
airflow/providers/mysql/transfers/__init__.py
airflow/providers/mysql/transfers/presto_to_mysql.py
airflow/providers/mysql/transfers/s3_to_mysql.py
airflow/providers/mysql/transfers/trino_to_mysql.py
airflow/providers/mysql/transfers/vertica_to_mysql.py
apache_airflow_providers_mysql-6.4.1.dist-info/entry_points.txt
apache_airflow_providers_mysql-6.4.1.dist-info/licenses/LICENSE
apache_airflow_providers_mysql-6.4.1.dist-info/licenses/NOTICE
apache_airflow_providers_mysql-6.4.1.dist-info/WHEEL
apache_airflow_providers_mysql-6.4.1.dist-info/METADATA
apache_airflow_providers_mysql-6.4.1.dist-info/RECORD
