Metadata-Version: 2.4
Name: apache-airflow-providers-mysql
Version: 6.4.1
Summary: Provider package apache-airflow-providers-mysql for Apache Airflow
Keywords: airflow-provider,mysql,airflow,integration
Author-email: Apache Software Foundation <dev@airflow.apache.org>
Maintainer-email: Apache Software Foundation <dev@airflow.apache.org>
Requires-Python: >=3.10
License-Expression: Apache-2.0
Classifier: Development Status :: 5 - Production/Stable
Classifier: Environment :: Console
Classifier: Environment :: Web Environment
Classifier: Intended Audience :: Developers
Classifier: Intended Audience :: System Administrators
Classifier: Framework :: Apache Airflow
Classifier: Framework :: Apache Airflow :: Provider
Classifier: Programming Language :: Python :: 3.10
Classifier: Programming Language :: Python :: 3.11
Classifier: Programming Language :: Python :: 3.12
Classifier: Programming Language :: Python :: 3.13
Classifier: Topic :: System :: Monitoring
License-File: LICENSE
License-File: NOTICE
Requires-Dist: apache-airflow>=2.11.0
Requires-Dist: apache-airflow-providers-common-compat>=1.12.0
Requires-Dist: apache-airflow-providers-common-sql>=1.20.0
Requires-Dist: mysqlclient>=2.2.5; sys_platform != "darwin"
Requires-Dist: mysql-connector-python>=9.1.0
Requires-Dist: aiomysql>=0.2.0
Requires-Dist: apache-airflow-providers-amazon ; extra == "amazon"
Requires-Dist: apache-airflow-providers-openlineage ; extra == "openlineage"
Requires-Dist: apache-airflow-providers-presto ; extra == "presto"
Requires-Dist: apache-airflow-providers-trino ; extra == "trino"
Requires-Dist: apache-airflow-providers-vertica ; extra == "vertica"
Project-URL: Bug Tracker, https://github.com/apache/airflow/issues
Project-URL: Changelog, https://airflow.apache.org/docs/apache-airflow-providers-mysql/6.4.1/changelog.html
Project-URL: Documentation, https://airflow.apache.org/docs/apache-airflow-providers-mysql/6.4.1
Project-URL: Mastodon, https://fosstodon.org/@airflow
Project-URL: Slack Chat, https://s.apache.org/airflow-slack
Project-URL: Source Code, https://github.com/apache/airflow
Project-URL: YouTube, https://www.youtube.com/channel/UCSXwxpWZQ7XZ1WL3wqevChA/
Provides-Extra: amazon
Provides-Extra: mysql-connector-python
Provides-Extra: openlineage
Provides-Extra: presto
Provides-Extra: trino
Provides-Extra: vertica
